compath_utils/__init__.py
compath_utils/exc.py
compath_utils/manager.py
compath_utils/models.py
compath_utils/utils.py
compath_utils/version.py
compath_utils-0.3.2.dist-info/LICENSE
compath_utils-0.3.2.dist-info/METADATA
compath_utils-0.3.2.dist-info/WHEEL
compath_utils-0.3.2.dist-info/top_level.txt
compath_utils-0.3.2.dist-info/RECORD
