Metadata-Version: 2.1
Name: compath-utils
Version: 0.3.2
Summary: A utilities package for ComPath
Home-page: https://github.com/compath/compath_utils
Author: Daniel Domingo-Fernández and Charles Tapley Hoyt
Author-email: daniel.domingo.fernandez@scai.fraunhofer.de
Maintainer: Daniel Domingo-Fernández
Maintainer-email: daniel.domingo.fernandez@scai.fraunhofer.de
License: MIT
Download-URL: https://pypi.org/project/compath-utils
Project-URL: Bug Tracker, https://github.com/compath/compath_utils/issues
Project-URL: Source Code, https://github.com/compath/compath_utils
Project-URL: Documentation, https://compath-utils.readthedocs.io
Keywords: Pathways,Systems Biology,Networks Biology,Curation
Platform: UNKNOWN
Classifier: Development Status :: 4 - Beta
Classifier: Environment :: Console
Classifier: Intended Audience :: Developers
Classifier: Intended Audience :: Science/Research
Classifier: License :: OSI Approved :: MIT License
Classifier: Operating System :: OS Independent
Classifier: Programming Language :: Python
Classifier: Programming Language :: Python :: 3.7
Classifier: Programming Language :: Python :: 3 :: Only
Classifier: Topic :: Scientific/Engineering :: Bio-Informatics
Requires-Python: >=3.7
Requires-Dist: bio2bel (>=0.3.2)
Requires-Dist: pybel (>=0.14.1)
Requires-Dist: sqlalchemy (==1.3.8)
Requires-Dist: pandas (==0.24.2)
Requires-Dist: click (==7.0)
Provides-Extra: docs
Requires-Dist: sphinx ; extra == 'docs'
Requires-Dist: sphinx-rtd-theme ; extra == 'docs'
Requires-Dist: sphinx-click ; extra == 'docs'
Requires-Dist: sphinx-autodoc-typehints ; extra == 'docs'
